postodon/__init__.py
postodon/append_post.py
postodon/select_post.py
postodon/submit_post.py
postodon/utils.py
postodon-0.0.5.dist-info/LICENSE
postodon-0.0.5.dist-info/METADATA
postodon-0.0.5.dist-info/WHEEL
postodon-0.0.5.dist-info/entry_points.txt
postodon-0.0.5.dist-info/RECORD
