Metadata-Version: 2.1
Name: postodon
Version: 0.0.5
Summary: Post to Mastodon
Home-page: https://github.com/msleigh/postodon
License: Apache-2.0
Author: msleigh
Author-email: msleigh@users.noreply.github.com
Requires-Python: >=3.8,<4.0
Classifier: Development Status :: 1 - Planning
Classifier: License :: OSI Approved :: Apache Software License
Classifier: Natural Language :: English
Classifier: Operating System :: OS Independent
Classifier: Programming Language :: Python :: 3
Classifier: Programming Language :: Python :: 3.8
Classifier: Programming Language :: Python :: 3.9
Classifier: Programming Language :: Python :: 3.10
Classifier: Programming Language :: Python :: 3.11
Classifier: Programming Language :: Python :: 3
Requires-Dist: platformdirs (>=4.0.0,<5.0.0)
Requires-Dist: requests (>=2.30.0,<3.0.0)
Requires-Dist: sphinx (>=7.0.1,<8.0.0)
Project-URL: Bug Tracker, https://github.com/msleigh/postodon/issues
Project-URL: CI, https://github.com/msleigh/postodon/actions
Project-URL: Changelog, https://github.com/msleigh/postodon/releases
